codecraft/__init__.py
codecraft/__main__.py
codecraft/_version.py
codecraft/analytics.py
codecraft/args.py
codecraft/args_formatter.py
codecraft/cli.py
codecraft/commands.py
codecraft/copypaste.py
codecraft/deprecated.py
codecraft/diffs.py
codecraft/dump.py
codecraft/editor.py
codecraft/exceptions.py
codecraft/format_settings.py
codecraft/gui.py
codecraft/help.py
codecraft/help_pats.py
codecraft/history.py
codecraft/io.py
codecraft/linter.py
codecraft/llm.py
codecraft/main.py
codecraft/mdstream.py
codecraft/models.py
codecraft/notion_command.py
codecraft/notion_integration.py
codecraft/onboarding.py
codecraft/prompts.py
codecraft/reasoning_tags.py
codecraft/repo.py
codecraft/repomap.py
codecraft/report.py
codecraft/run_cmd.py
codecraft/scrape.py
codecraft/sendchat.py
codecraft/special.py
codecraft/urls.py
codecraft/utils.py
codecraft/versioncheck.py
codecraft/voice.py
codecraft/waiting.py
codecraft/watch.py
codecraft/watch_prompts.py
codecraft/coders/__init__.py
codecraft/coders/architect_coder.py
codecraft/coders/architect_prompts.py
codecraft/coders/ask_coder.py
codecraft/coders/ask_prompts.py
codecraft/coders/base_coder.py
codecraft/coders/base_prompts.py
codecraft/coders/chat_chunks.py
codecraft/coders/context_coder.py
codecraft/coders/context_prompts.py
codecraft/coders/editblock_coder.py
codecraft/coders/editblock_fenced_coder.py
codecraft/coders/editblock_fenced_prompts.py
codecraft/coders/editblock_func_coder.py
codecraft/coders/editblock_func_prompts.py
codecraft/coders/editblock_prompts.py
codecraft/coders/editor_diff_fenced_coder.py
codecraft/coders/editor_diff_fenced_prompts.py
codecraft/coders/editor_editblock_coder.py
codecraft/coders/editor_editblock_prompts.py
codecraft/coders/editor_whole_coder.py
codecraft/coders/editor_whole_prompts.py
codecraft/coders/help_coder.py
codecraft/coders/help_prompts.py
codecraft/coders/patch_coder.py
codecraft/coders/patch_prompts.py
codecraft/coders/search_replace.py
codecraft/coders/single_wholefile_func_coder.py
codecraft_chat-0.83.3.dev11.dist-info/licenses/LICENSE.txt
codecraft_chat-0.83.3.dev11.dist-info/METADATA
codecraft_chat-0.83.3.dev11.dist-info/WHEEL
codecraft_chat-0.83.3.dev11.dist-info/entry_points.txt
codecraft_chat-0.83.3.dev11.dist-info/top_level.txt
codecraft_chat-0.83.3.dev11.dist-info/RECORD
